GDV_distribute_and_mark/__init__.py
GDV_distribute_and_mark/class_definition_logic.py
GDV_distribute_and_mark/db.py
GDV_distribute_and_mark/main.py
GDV_distribute_and_mark/parsing.py
GDV_distribute_and_mark/resource_manager.py
GDV_distribute_and_mark/assets/ico.png
GDV_distribute_and_mark-0.0.1.dist-info/LICENSE
GDV_distribute_and_mark-0.0.1.dist-info/METADATA
GDV_distribute_and_mark-0.0.1.dist-info/WHEEL
GDV_distribute_and_mark-0.0.1.dist-info/entry_points.txt
GDV_distribute_and_mark-0.0.1.dist-info/top_level.txt
GDV_distribute_and_mark-0.0.1.dist-info/RECORD
