Metadata-Version: 2.1
Name: GDV_distribute_and_mark
Version: 0.0.1
Summary: Mark classes for GDV scans. 
Author-email: The220th <The220th@gmail.com>
Project-URL: Homepage, https://github.com/The220th/GDV_distribute_and_mark
Project-URL: Issues, https://github.com/The220th/GDV_distribute_and_mark/issues
Classifier: Programming Language :: Python :: 3
Classifier: License :: OSI Approved :: MIT License
Classifier: Operating System :: OS Independent
Requires-Python: >=3.7
License-File: LICENSE
Requires-Dist: pillow
Requires-Dist: argparse
Requires-Dist: ksupk
Requires-Dist: matplotlib
